<annotation>
	<folder>images</folder>
	<filename>damagedimage025_jpg.rf.3140026bae05c07b674061fb824e9c77.jpg</filename>
	<path>D:\Jojo_Data\python\ai\pythonProject\object_detection_project\barcode-and-qr\images\damagedimage025_jpg.rf.3140026bae05c07b674061fb824e9c77.jpg</path>
	<source>
		<database>Unknown</database>
	</source>
	<size>
		<width>416</width>
		<height>416</height>
		<depth>3</depth>
	</size>
	<segmented>0</segmented>
	<object>
		<name>qr</name>
		<pose>Unspecified</pose>
		<truncated>0</truncated>
		<difficult>0</difficult>
		<bndbox>
			<xmin>46</xmin>
			<ymin>65</ymin>
			<xmax>349</xmax>
			<ymax>345</ymax>
		</bndbox>
	</object>
	<object>
		<name>barcode</name>
		<pose>Unspecified</pose>
		<truncated>1</truncated>
		<difficult>1</difficult>
		<bndbox>
			<xmin>1</xmin>
			<ymin>373</ymin>
			<xmax>416</xmax>
			<ymax>416</ymax>
		</bndbox>
	</object>
</annotation>
