<annotation>
	<folder>images</folder>
	<filename>nominalimage004_jpg.rf.0764dc73a584184965ead0ba11cfc28d.jpg</filename>
	<path>D:\Jojo_Data\python\ai\pythonProject\object_detection_project\barcode-and-qr\images\nominalimage004_jpg.rf.0764dc73a584184965ead0ba11cfc28d.jpg</path>
	<source>
		<database>Unknown</database>
	</source>
	<size>
		<width>416</width>
		<height>416</height>
		<depth>3</depth>
	</size>
	<segmented>0</segmented>
	<object>
		<name>qr</name>
		<pose>Unspecified</pose>
		<truncated>0</truncated>
		<difficult>0</difficult>
		<bndbox>
			<xmin>140</xmin>
			<ymin>76</ymin>
			<xmax>221</xmax>
			<ymax>191</ymax>
		</bndbox>
	</object>
	<object>
		<name>qr</name>
		<pose>Unspecified</pose>
		<truncated>0</truncated>
		<difficult>0</difficult>
		<bndbox>
			<xmin>238</xmin>
			<ymin>73</ymin>
			<xmax>328</xmax>
			<ymax>188</ymax>
		</bndbox>
	</object>
</annotation>
